klym_telemetry/__init__.py
klym_telemetry/helpers.py
klym_telemetry/utils.py
klym_telemetry/instrumenters/__init__.py
klym_telemetry/instrumenters/aiohttp.py
klym_telemetry/instrumenters/airflow.py
klym_telemetry/instrumenters/base.py
klym_telemetry/instrumenters/celery.py
klym_telemetry/instrumenters/django.py
klym_telemetry/instrumenters/fastapi.py
klym_telemetry/instrumenters/module_import.py
klym_telemetry/instrumenters/psycopg2.py
klym_telemetry/instrumenters/python.py
klym_telemetry/instrumenters/requests.py
klym_telemetry-0.1.12.10.dist-info/METADATA
klym_telemetry-0.1.12.10.dist-info/WHEEL
klym_telemetry-0.1.12.10.dist-info/top_level.txt
klym_telemetry-0.1.12.10.dist-info/RECORD
