Metadata-Version: 2.1
Name: klym-telemetry
Version: 0.1.12.10
Summary: Scaffold library
Home-page: https://dummy.readthedocs.io/
Author: Klym Telemetry
Author-email: example@email.com
License: MIT
Platform: UNKNOWN
Classifier: Intended Audience :: Developers
Classifier: License :: OSI Approved :: MIT License
Classifier: Programming Language :: Python
Classifier: Programming Language :: Python :: 3
Classifier: Programming Language :: Python :: 3.6
Classifier: Programming Language :: Python :: 3.7
Classifier: Programming Language :: Python :: 3.8
Classifier: Programming Language :: Python :: 3.9
Classifier: Programming Language :: Python :: 3.10
Classifier: Programming Language :: Python :: 3.11
Classifier: Operating System :: OS Independent
Requires-Python: >=3.6
Requires-Dist: opentelemetry-exporter-otlp-proto-grpc (~=1.20.0)
Requires-Dist: opentelemetry-instrumentation-aiohttp-client (==0.41b0)
Requires-Dist: opentelemetry-instrumentation-celery (==0.41b0)
Requires-Dist: opentelemetry-instrumentation-django (==0.41b0)
Requires-Dist: opentelemetry-instrumentation-fastapi (==0.41b0)
Requires-Dist: opentelemetry-instrumentation-psycopg2 (==0.41b0)
Requires-Dist: opentelemetry-instrumentation-requests (==0.41b0)
Requires-Dist: opentelemetry-instrumentation-sqlalchemy (==0.41b0)
Requires-Dist: opentelemetry-instrumentation (==0.41b0)
Requires-Dist: opentelemetry-propagator-aws-xray (~=1.0.1)
Requires-Dist: opentelemetry-sdk-extension-aws (~=2.0.1)
Requires-Dist: opentelemetry-semantic-conventions (==0.41b0)
